Workbook

Sheet README
A1: Kestrel Health Services - 3-year workforce scenario model (FY2027-FY2029)
A2: FICTIONAL ORGANISATION. Internal workforce figures are SYNTHETIC; labour-market inputs are REAL public data.
A4: How to use
A5: 1. Choose a scenario in Scenarios!C3 (A Baseline / B Growth / C Constraint).
A6: 2. Edit yellow cells (inputs) on 'Scenarios' and 'Inputs'. Every other number is a formula.
A7: 3. Results: 'Model' (family x year detail) and 'Summary' (totals and checks).
A9: Stock-and-flow identity
A10: HC end = HC start + Hires + Graduates + EN->RN in + Net transfers - Separations - EN->RN out
A11: Required hires = MAX(0, (Demand FTE - HC pre-hire x FTE per head) / FTE per head); Hires = MIN(Required, Capacity)
A12: Gap FTE = Demand FTE - Supply FTE (positive = shortage). Agency covers a measured share of the shortage.
A14: Provenance colours
A15: Green = real public data (ABS / JSA)
... A19: Validation: the Python engine (src/scenario_model.py, family_inputs) reproduces every Model cell; see 'Checks'.

Sheet Scenarios
A1: Scenario parameters
B3: Selected scenario: | C3: A Baseline
A5: Parameter | B5: A Baseline | C5: B Growth | D5: C Constraint | E5: ACTIVE | F5: Provenance | G5: Evidence
A6: Demand growth add-on: clinical (pp) | B6: 0 | C6: 0.02 | D6: 0 | E6: =INDEX(B6:D6,MATCH($C$3,$B$5:$D$5,0)) | F6: ILLUSTRATIVE | G6: Growth: service expansion, bounded by ABS HCSA filled jobs 5-yr CAGR
A7: Demand growth add-on: non-clinical (pp) | B7: 0 | C7: 0.005 | D7: 0 | E7: =INDEX(B7:D7,MATCH($C$3,$B$5:$D$5,0)) | F7: ILLUSTRATIVE | G7: Growth scenario only
A8: Attrition multiplier | B8: 1 | C8: 1 | D8: 1.224 | E8: =INDEX(B8:D8,MATCH($C$3,$B$5:$D$5,0)) | F8: SYNTHETIC | G8: Constraint = KHS FY2023/FY2026 turnover ratio
A9: Capacity multiplier: OSL shortage occupations | B9: 1 | C9: 1 | D9: 0.731 | E9: =INDEX(B9:D9,MATCH($C$3,$B$5:$D$5,0)) | F9: REAL | G9: Constraint = JSA OSL 2026 fill rate shortage/no-shortage (57%/78%)
A10: Graduate intake multiplier | B10: 1 | C10: 1 | D10: 0.75 | E10: =INDEX(B10:D10,MATCH($C$3,$B$5:$D$5,0)) | F10: ILLUSTRATIVE | G10: Constraint: fewer graduate placements
A11: Wage growth p.a. | B11: 0.0371 | C11: 0.0371 | D11: 0.0471 | E11: =INDEX(B11:D11,MATCH($C$3,$B$5:$D$5,0)) | F11: REAL | G11: ABS WPI HCSA avg YoY last 8 quarters; Constraint +1pp (illustrative)
A12: Agency premium (x employee cost) | B12: 1.65 | C12: 1.65 | D12: 1.65 | E12: =INDEX(B12:D12,MATCH($C$3,$B$5:$D$5,0)) | F12: ILLUSTRATIVE | G12: Assumed
A13: EN->RN conversion rate p.a. | B13: 0.055137845 | C13: 0.055137845 | D13: 0.055137845 | E13: =INDEX(B13:D13,MATCH($C$3,$B$5:$D$5,0)) | F13: SYNTHETIC | G13: KHS role-change history
A14: Graduate RNs per year | B14: 16 | C14: 16 | D14: 16 | E14: =INDEX(B14:D14,MATCH($C$3,$B$5:$D$5,0)) | F14: SYNTHETIC | G14: KHS average FY2023-26
A15: On-cost factor | B15: 1.25 | C15: 1.25 | D15: 1.25 | E15: =INDEX(B15:D15,MATCH($C$3,$B$5:$D$5,0)) | F15: ILLUSTRATIVE | G15: 12% super guarantee (legislated) + other on-costs (assumed)

Sheet Inputs
A1: Job family | B1: Headcount 30 Jun 2026 | C1: FTE per head | D1: Demand FTE FY2026 (establishment) | E1: Base demand growth p.a. | F1: Clinical? (1/0) | G1: Attrition rate p.a. | H1: Recruitment capacity (hires/yr) | I1: OSL shortage occupation (1/0) | J1: Graduate share | K1: Net internal transfers p.a. | L1: Base salary per FTE ($) | M1: Agency cover of shortage | N1: Cost per hire ($)
A2: Provenance -> | B2: SYNTHETIC | C2: SYNTHETIC | D2: SYNTHETIC | E2: REAL | G2: SYNTHETIC | H2: SYNTHETIC | I2: REAL | J2: SYNTHETIC | K2: SYNTHETIC | L2: SYNTHETIC | M2: SYNTHETIC | N2: ILLUSTRATIVE
A3: Registered Nurse | B3: 686 | C3: 0.82259475 | D3: 552.7 | E3: 0.023661072 | F3: 1 | G3: 0.11056252 | H3: 113 | I3: 1 | J3: 1 | K3: 0 | L3: 122229.01 | M3: 0.551 | N3: 9469.0265
A4: Midwife | B4: 56 | C4: 0.85535714 | D4: 47.9 | E4: 0.024261225 | F4: 1 | G4: 0.08169665 | H4: 11 | I4: 1 | J4: 0 | K4: 0 | L4: 123527.35 | M4: 0.569 | N4: 10363.636
A5: Enrolled Nurse | B5: 151 | C5: 0.7615894 | D5: 125.8 | E5: 0.019760077 | F5: 1 | G5: 0.12897315 | H5: 56 | I5: 0 | J5: 0 | K5: 0 | L5: 89721.043 | M5: 0.399 | N5: 9571.4286
A6: Medical Practitioner | B6: 136 | C6: 0.90441176 | D6: 136.1 | E6: 0.029162475 | F6: 1 | G6: 0.11643919 | H6: 23 | I6: 1 | J6: 0 | K6: 0 | L6: 270965.77 | M6: 0.627 | N6: 8782.6087
A7: Allied Health | B7: 169 | C7: 0.85857988 | D7: 155.3 | E7: 0.030262756 | F7: 1 | G7: 0.12495594 | H7: 35 | I7: 1 | J7: 0 | K7: 0 | L7: 114279.53 | M7: 0.302 | N7: 10114.286
A8: Care Worker | B8: 361 | C8: 0.71689751 | D8: 288.6 | E8: 0.01835972 | F8: 1 | G8: 0.26127371 | H8: 131 | I8: 1 | J8: 0 | K8: 0 | L8: 77180.023 | M8: 0.459 | N8: 9725.1908
A9: Administration | B9: 247 | C9: 0.87813765 | D9: 232.6 | E9: 0.0093574243 | F9: 0 | G9: 0.12268638 | H9: 53 | I9: 0 | J9: 0 | K9: 0 | L9: 87029.184 | M9: 0.101 | N9: 9320.7547
A10: Support Services | B10: 184 | C10: 0.85054348 | D10: 162.8 | E10: 0.0049563019 | F10: 0 | G10: 0.14323785 | H10: 56 | I10: 0 | J10: 0 | K10: 0 | L10: 75276.933 | M10: 0.253 | N10: 9142.8571

Sheet Model
A1: Year | B1: t | C1: Job family | D1: Demand growth | E1: Demand FTE | F1: HC start | G1: Attrition | H1: Separations | I1: EN->RN out | J1: EN->RN in | K1: Graduates | L1: Net transfers | M1: HC pre-hire | N1: FTE/head | O1: Required hires | P1: Capacity | Q1: Hires | R1: HC end | S1: Supply FTE | T1: Gap FTE | U1: Shortage FTE | V1: Agency FTE | W1: Unfilled FTE | X1: Wage index | Y1: Employee cost | Z1: Agency cost | AA1: Recruitment cost | AB1: Total cost | AC1: Identity check
A2: FY2027 | B2: 1 | C2: Registered Nurse | D2: =Inputs!$E$3+IF(Inputs!$F$3=1,Scenarios!$E$6,Scenarios!$E$7) | E2: =Inputs!$D$3*(1+D2) | F2: =Inputs!$B$3 | G2: =Inputs!$G$3*Scenarios!$E$8 | H2: =F2*G2 | I2: =0 | J2: =I4 | K2: =Inputs!$J$3*Scenarios!$E$14*Scenarios!$E$10 | L2: =Inputs!$K$3 | M2: =F2-H2-I2+J2+K2+L2 | N2: =Inputs!$C$3 | O2: =MAX(0,(E2-M2*N2)/N2) | P2: =Inputs!$H$3*IF(Inputs!$I$3=1,Scenarios!$E$9,1) | Q2: =MIN(O2,P2) | R2: =M2+Q2 | S2: =R2*N2 | T2: =E2-S2 | U2: =MAX(0,T2) | V2: =U2*Inputs!$M$3 | W2: =U2-V2 | X2: =(1+Scenarios!$E$11)^B2 | Y2: =((F2*N2+S2)/2)*Inputs!$L$3*X2*Scenarios!$E$15 | Z2: =V2*Inputs!$L$3*X2*Scenarios!$E$12 | AA2: =Q2*Inputs!$N$3 | AB2: =Y2+Z2+AA2 | AC2: =F2+Q2+K2+J2+L2-H2-I2-R2
A3: FY2027 | B3: 1 | C3: Midwife | D3: =Inputs!$E$4+IF(Inputs!$F$4=1,Scenarios!$E$6,Scenarios!$E$7) | E3: =Inputs!$D$4*(1+D3) | F3: =Inputs!$B$4 | G3: =Inputs!$G$4*Scenarios!$E$8 | H3: =F3*G3 | I3: =0 | J3: =0 | K3: =Inputs!$J$4*Scenarios!$E$14*Scenarios!$E$10 | L3: =Inputs!$K$4 | M3: =F3-H3-I3+J3+K3+L3 | N3: =Inputs!$C$4 | O3: =MAX(0,(E3-M3*N3)/N3) | P3: =Inputs!$H$4*IF(Inputs!$I$4=1,Scenarios!$E$9,1) | Q3: =MIN(O3,P3) | R3: =M3+Q3 | S3: =R3*N3 | T3: =E3-S3 | U3: =MAX(0,T3) | V3: =U3*Inputs!$M$4 | W3: =U3-V3 | X3: =(1+Scenarios!$E$11)^B3 | Y3: =((F3*N3+S3)/2)*Inputs!$L$4*X3*Scenarios!$E$15 | Z3: =V3*Inputs!$L$4*X3*Scenarios!$E$12 | AA3: =Q3*Inputs!$N$4 | AB3: =Y3+Z3+AA3 | AC3: =F3+Q3+K3+J3+L3-H3-I3-R3
A4: FY2027 | B4: 1 | C4: Enrolled Nurse | D4: =Inputs!$E$5+IF(Inputs!$F$5=1,Scenarios!$E$6,Scenarios!$E$7) | E4: =Inputs!$D$5*(1+D4) | F4: =Inputs!$B$5 | G4: =Inputs!$G$5*Scenarios!$E$8 | H4: =F4*G4 | I4: =F4*Scenarios!$E$13 | J4: =0 | K4: =Inputs!$J$5*Scenarios!$E$14*Scenarios!$E$10 | L4: =Inputs!$K$5 | M4: =F4-H4-I4+J4+K4+L4 | N4: =Inputs!$C$5 | O4: =MAX(0,(E4-M4*N4)/N4) | P4: =Inputs!$H$5*IF(Inputs!$I$5=1,Scenarios!$E$9,1) | Q4: =MIN(O4,P4) | R4: =M4+Q4 | S4: =R4*N4 | T4: =E4-S4 | U4: =MAX(0,T4) | V4: =U4*Inputs!$M$5 | W4: =U4-V4 | X4: =(1+Scenarios!$E$11)^B4 | Y4: =((F4*N4+S4)/2)*Inputs!$L$5*X4*Scenarios!$E$15 | Z4: =V4*Inputs!$L$5*X4*Scenarios!$E$12 | AA4: =Q4*Inputs!$N$5 | AB4: =Y4+Z4+AA4 | AC4: =F4+Q4+K4+J4+L4-H4-I4-R4
A5: FY2027 | B5: 1 | C5: Medical Practitioner | D5: =Inputs!$E$6+IF(Inputs!$F$6=1,Scenarios!$E$6,Scenarios!$E$7) | E5: =Inputs!$D$6*(1+D5) | F5: =Inputs!$B$6 | G5: =Inputs!$G$6*Scenarios!$E$8 | H5: =F5*G5 | I5: =0 | J5: =0 | K5: =Inputs!$J$6*Scenarios!$E$14*Scenarios!$E$10 | L5: =Inputs!$K$6 | M5: =F5-H5-I5+J5+K5+L5 | N5: =Inputs!$C$6 | O5: =MAX(0,(E5-M5*N5)/N5) | P5: =Inputs!$H$6*IF(Inputs!$I$6=1,Scenarios!$E$9,1) | Q5: =MIN(O5,P5) | R5: =M5+Q5 | S5: =R5*N5 | T5: =E5-S5 | U5: =MAX(0,T5) | V5: =U5*Inputs!$M$6 | W5: =U5-V5 | X5: =(1+Scenarios!$E$11)^B5 | Y5: =((F5*N5+S5)/2)*Inputs!$L$6*X5*Scenarios!$E$15 | Z5: =V5*Inputs!$L$6*X5*Scenarios!$E$12 | AA5: =Q5*Inputs!$N$6 | AB5: =Y5+Z5+AA5 | AC5: =F5+Q5+K5+J5+L5-H5-I5-R5
A6: FY2027 | B6: 1 | C6: Allied Health | D6: =Inputs!$E$7+IF(Inputs!$F$7=1,Scenarios!$E$6,Scenarios!$E$7) | E6: =Inputs!$D$7*(1+D6) | F6: =Inputs!$B$7 | G6: =Inputs!$G$7*Scenarios!$E$8 | H6: =F6*G6 | I6: =0 | J6: =0 | K6: =Inputs!$J$7*Scenarios!$E$14*Scenarios!$E$10 | L6: =Inputs!$K$7 | M6: =F6-H6-I6+J6+K6+L6 | N6: =Inputs!$C$7 | O6: =MAX(0,(E6-M6*N6)/N6) | P6: =Inputs!$H$7*IF(Inputs!$I$7=1,Scenarios!$E$9,1) | Q6: =MIN(O6,P6) | R6: =M6+Q6 | S6: =R6*N6 | T6: =E6-S6 | U6: =MAX(0,T6) | V6: =U6*Inputs!$M$7 | W6: =U6-V6 | X6: =(1+Scenarios!$E$11)^B6 | Y6: =((F6*N6+S6)/2)*Inputs!$L$7*X6*Scenarios!$E$15 | Z6: =V6*Inputs!$L$7*X6*Scenarios!$E$12 | AA6: =Q6*Inputs!$N$7 | AB6: =Y6+Z6+AA6 | AC6: =F6+Q6+K6+J6+L6-H6-I6-R6
A7: FY2027 | B7: 1 | C7: Care Worker | D7: =Inputs!$E$8+IF(Inputs!$F$8=1,Scenarios!$E$6,Scenarios!$E$7) | E7: =Inputs!$D$8*(1+D7) | F7: =Inputs!$B$8 | G7: =Inputs!$G$8*Scenarios!$E$8 | H7: =F7*G7 | I7: =0 | J7: =0 | K7: =Inputs!$J$8*Scenarios!$E$14*Scenarios!$E$10 | L7: =Inputs!$K$8 | M7: =F7-H7-I7+J7+K7+L7 | N7: =Inputs!$C$8 | O7: =MAX(0,(E7-M7*N7)/N7) | P7: =Inputs!$H$8*IF(Inputs!$I$8=1,Scenarios!$E$9,1) | Q7: =MIN(O7,P7) | R7: =M7+Q7 | S7: =R7*N7 | T7: =E7-S7 | U7: =MAX(0,T7) | V7: =U7*Inputs!$M$8 | W7: =U7-V7 | X7: =(1+Scenarios!$E$11)^B7 | Y7: =((F7*N7+S7)/2)*Inputs!$L$8*X7*Scenarios!$E$15 | Z7: =V7*Inputs!$L$8*X7*Scenarios!$E$12 | AA7: =Q7*Inputs!$N$8 | AB7: =Y7+Z7+AA7 | AC7: =F7+Q7+K7+J7+L7-H7-I7-R7
A8: FY2027 | B8: 1 | C8: Administration | D8: =Inputs!$E$9+IF(Inputs!$F$9=1,Scenarios!$E$6,Scenarios!$E$7) | E8: =Inputs!$D$9*(1+D8) | F8: =Inputs!$B$9 | G8: =Inputs!$G$9*Scenarios!$E$8 | H8: =F8*G8 | I8: =0 | J8: =0 | K8: =Inputs!$J$9*Scenarios!$E$14*Scenarios!$E$10 | L8: =Inputs!$K$9 | M8: =F8-H8-I8+J8+K8+L8 | N8: =Inputs!$C$9 | O8: =MAX(0,(E8-M8*N8)/N8) | P8: =Inputs!$H$9*IF(Inputs!$I$9=1,Scenarios!$E$9,1) | Q8: =MIN(O8,P8) | R8: =M8+Q8 | S8: =R8*N8 | T8: =E8-S8 | U8: =MAX(0,T8) | V8: =U8*Inputs!$M$9 | W8: =U8-V8 | X8: =(1+Scenarios!$E$11)^B8 | Y8: =((F8*N8+S8)/2)*Inputs!$L$9*X8*Scenarios!$E$15 | Z8: =V8*Inputs!$L$9*X8*Scenarios!$E$12 | AA8: =Q8*Inputs!$N$9 | AB8: =Y8+Z8+AA8 | AC8: =F8+Q8+K8+J8+L8-H8-I8-R8
A9: FY2027 | B9: 1 | C9: Support Services | D9: =Inputs!$E$10+IF(Inputs!$F$10=1,Scenarios!$E$6,Scenarios!$E$7) | E9: =Inputs!$D$10*(1+D9) | F9: =Inputs!$B$10 | G9: =Inputs!$G$10*Scenarios!$E$8 | H9: =F9*G9 | I9: =0 | J9: =0 | K9: =Inputs!$J$10*Scenarios!$E$14*Scenarios!$E$10 | L9: =Inputs!$K$10 | M9: =F9-H9-I9+J9+K9+L9 | N9: =Inputs!$C$10 | O9: =MAX(0,(E9-M9*N9)/N9) | P9: =Inputs!$H$10*IF(Inputs!$I$10=1,Scenarios!$E$9,1) | Q9: =MIN(O9,P9) | R9: =M9+Q9 | S9: =R9*N9 | T9: =E9-S9 | U9: =MAX(0,T9) | V9: =U9*Inputs!$M$10 | W9: =U9-V9 | X9: =(1+Scenarios!$E$11)^B9 | Y9: =((F9*N9+S9)/2)*Inputs!$L$10*X9*Scenarios!$E$15 | Z9: =V9*Inputs!$L$10*X9*Scenarios!$E$12 | AA9: =Q9*Inputs!$N$10 | AB9: =Y9+Z9+AA9 | AC9: =F9+Q9+K9+J9+L9-H9-I9-R9
A10: FY2028 | B10: 2 | C10: Registered Nurse | D10: =Inputs!$E$3+IF(Inputs!$F$3=1,Scenarios!$E$6,Scenarios!$E$7) | E10: =E2*(1+D10) | F10: =R2 | G10: =Inputs!$G$3*Scenarios!$E$8 | H10: =F10*G10 | I10: =0 | J10: =I12 | K10: =Inputs!$J$3*Scenarios!$E$14*Scenarios!$E$10 | L10: =Inputs!$K$3 | M10: =F10-H10-I10+J10+K10+L10 | N10: =Inputs!$C$3 | O10: =MAX(0,(E10-M10*N10)/N10) | P10: =Inputs!$H$3*IF(Inputs!$I$3=1,Scenarios!$E$9,1) | Q10: =MIN(O10,P10) | R10: =M10+Q10 | S10: =R10*N10 | T10: =E10-S10 | U10: =MAX(0,T10) | V10: =U10*Inputs!$M$3 | W10: =U10-V10 | X10: =(1+Scenarios!$E$11)^B10 | Y10: =((F10*N10+S10)/2)*Inputs!$L$3*X10*Scenarios!$E$15 | Z10: =V10*Inputs!$L$3*X10*Scenarios!$E$12 | AA10: =Q10*Inputs!$N$3 | AB10: =Y10+Z10+AA10 | AC10: =F10+Q10+K10+J10+L10-H10-I10-R10
A11: FY2028 | B11: 2 | C11: Midwife | D11: =Inputs!$E$4+IF(Inputs!$F$4=1,Scenarios!$E$6,Scenarios!$E$7) | E11: =E3*(1+D11) | F11: =R3 | G11: =Inputs!$G$4*Scenarios!$E$8 | H11: =F11*G11 | I11: =0 | J11: =0 | K11: =Inputs!$J$4*Scenarios!$E$14*Scenarios!$E$10 | L11: =Inputs!$K$4 | M11: =F11-H11-I11+J11+K11+L11 | N11: =Inputs!$C$4 | O11: =MAX(0,(E11-M11*N11)/N11) | P11: =Inputs!$H$4*IF(Inputs!$I$4=1,Scenarios!$E$9,1) | Q11: =MIN(O11,P11) | R11: =M11+Q11 | S11: =R11*N11 | T11: =E11-S11 | U11: =MAX(0,T11) | V11: =U11*Inputs!$M$4 | W11: =U11-V11 | X11: =(1+Scenarios!$E$11)^B11 | Y11: =((F11*N11+S11)/2)*Inputs!$L$4*X11*Scenarios!$E$15 | Z11: =V11*Inputs!$L$4*X11*Scenarios!$E$12 | AA11: =Q11*Inputs!$N$4 | AB11: =Y11+Z11+AA11 | AC11: =F11+Q11+K11+J11+L11-H11-I11-R11
A12: FY2028 | B12: 2 | C12: Enrolled Nurse | D12: =Inputs!$E$5+IF(Inputs!$F$5=1,Scenarios!$E$6,Scenarios!$E$7) | E12: =E4*(1+D12) | F12: =R4 | G12: =Inputs!$G$5*Scenarios!$E$8 | H12: =F12*G12 | I12: =F12*Scenarios!$E$13 | J12: =0 | K12: =Inputs!$J$5*Scenarios!$E$14*Scenarios!$E$10 | L12: =Inputs!$K$5 | M12: =F12-H12-I12+J12+K12+L12 | N12: =Inputs!$C$5 | O12: =MAX(0,(E12-M12*N12)/N12) | P12: =Inputs!$H$5*IF(Inputs!$I$5=1,Scenarios!$E$9,1) | Q12: =MIN(O12,P12) | R12: =M12+Q12 | S12: =R12*N12 | T12: =E12-S12 | U12: =MAX(0,T12) | V12: =U12*Inputs!$M$5 | W12: =U12-V12 | X12: =(1+Scenarios!$E$11)^B12 | Y12: =((F12*N12+S12)/2)*Inputs!$L$5*X12*Scenarios!$E$15 | Z12: =V12*Inputs!$L$5*X12*Scenarios!$E$12 | AA12: =Q12*Inputs!$N$5 | AB12: =Y12+Z12+AA12 | AC12: =F12+Q12+K12+J12+L12-H12-I12-R12
A13: FY2028 | B13: 2 | C13: Medical Practitioner | D13: =Inputs!$E$6+IF(Inputs!$F$6=1,Scenarios!$E$6,Scenarios!$E$7) | E13: =E5*(1+D13) | F13: =R5 | G13: =Inputs!$G$6*Scenarios!$E$8 | H13: =F13*G13 | I13: =0 | J13: =0 | K13: =Inputs!$J$6*Scenarios!$E$14*Scenarios!$E$10 | L13: =Inputs!$K$6 | M13: =F13-H13-I13+J13+K13+L13 | N13: =Inputs!$C$6 | O13: =MAX(0,(E13-M13*N13)/N13) | P13: =Inputs!$H$6*IF(Inputs!$I$6=1,Scenarios!$E$9,1) | Q13: =MIN(O13,P13) | R13: =M13+Q13 | S13: =R13*N13 | T13: =E13-S13 | U13: =MAX(0,T13) | V13: =U13*Inputs!$M$6 | W13: =U13-V13 | X13: =(1+Scenarios!$E$11)^B13 | Y13: =((F13*N13+S13)/2)*Inputs!$L$6*X13*Scenarios!$E$15 | Z13: =V13*Inputs!$L$6*X13*Scenarios!$E$12 | AA13: =Q13*Inputs!$N$6 | AB13: =Y13+Z13+AA13 | AC13: =F13+Q13+K13+J13+L13-H13-I13-R13
A14: FY2028 | B14: 2 | C14: Allied Health | D14: =Inputs!$E$7+IF(Inputs!$F$7=1,Scenarios!$E$6,Scenarios!$E$7) | E14: =E6*(1+D14) | F14: =R6 | G14: =Inputs!$G$7*Scenarios!$E$8 | H14: =F14*G14 | I14: =0 | J14: =0 | K14: =Inputs!$J$7*Scenarios!$E$14*Scenarios!$E$10 | L14: =Inputs!$K$7 | M14: =F14-H14-I14+J14+K14+L14 | N14: =Inputs!$C$7 | O14: =MAX(0,(E14-M14*N14)/N14) | P14: =Inputs!$H$7*IF(Inputs!$I$7=1,Scenarios!$E$9,1) | Q14: =MIN(O14,P14) | R14: =M14+Q14 | S14: =R14*N14 | T14: =E14-S14 | U14: =MAX(0,T14) | V14: =U14*Inputs!$M$7 | W14: =U14-V14 | X14: =(1+Scenarios!$E$11)^B14 | Y14: =((F14*N14+S14)/2)*Inputs!$L$7*X14*Scenarios!$E$15 | Z14: =V14*Inputs!$L$7*X14*Scenarios!$E$12 | AA14: =Q14*Inputs!$N$7 | AB14: =Y14+Z14+AA14 | AC14: =F14+Q14+K14+J14+L14-H14-I14-R14
A15: FY2028 | B15: 2 | C15: Care Worker | D15: =Inputs!$E$8+IF(Inputs!$F$8=1,Scenarios!$E$6,Scenarios!$E$7) | E15: =E7*(1+D15) | F15: =R7 | G15: =Inputs!$G$8*Scenarios!$E$8 | H15: =F15*G15 | I15: =0 | J15: =0 | K15: =Inputs!$J$8*Scenarios!$E$14*Scenarios!$E$10 | L15: =Inputs!$K$8 | M15: =F15-H15-I15+J15+K15+L15 | N15: =Inputs!$C$8 | O15: =MAX(0,(E15-M15*N15)/N15) | P15: =Inputs!$H$8*IF(Inputs!$I$8=1,Scenarios!$E$9,1) | Q15: =MIN(O15,P15) | R15: =M15+Q15 | S15: =R15*N15 | T15: =E15-S15 | U15: =MAX(0,T15) | V15: =U15*Inputs!$M$8 | W15: =U15-V15 | X15: =(1+Scenarios!$E$11)^B15 | Y15: =((F15*N15+S15)/2)*Inputs!$L$8*X15*Scenarios!$E$15 | Z15: =V15*Inputs!$L$8*X15*Scenarios!$E$12 | AA15: =Q15*Inputs!$N$8 | AB15: =Y15+Z15+AA15 | AC15: =F15+Q15+K15+J15+L15-H15-I15-R15
A16: FY2028 | B16: 2 | C16: Administration | D16: =Inputs!$E$9+IF(Inputs!$F$9=1,Scenarios!$E$6,Scenarios!$E$7) | E16: =E8*(1+D16) | F16: =R8 | G16: =Inputs!$G$9*Scenarios!$E$8 | H16: =F16*G16 | I16: =0 | J16: =0 | K16: =Inputs!$J$9*Scenarios!$E$14*Scenarios!$E$10 | L16: =Inputs!$K$9 | M16: =F16-H16-I16+J16+K16+L16 | N16: =Inputs!$C$9 | O16: =MAX(0,(E16-M16*N16)/N16) | P16: =Inputs!$H$9*IF(Inputs!$I$9=1,Scenarios!$E$9,1) | Q16: =MIN(O16,P16) | R16: =M16+Q16 | S16: =R16*N16 | T16: =E16-S16 | U16: =MAX(0,T16) | V16: =U16*Inputs!$M$9 | W16: =U16-V16 | X16: =(1+Scenarios!$E$11)^B16 | Y16: =((F16*N16+S16)/2)*Inputs!$L$9*X16*Scenarios!$E$15 | Z16: =V16*Inputs!$L$9*X16*Scenarios!$E$12 | AA16: =Q16*Inputs!$N$9 | AB16: =Y16+Z16+AA16 | AC16: =F16+Q16+K16+J16+L16-H16-I16-R16
A17: FY2028 | B17: 2 | C17: Support Services | D17: =Inputs!$E$10+IF(Inputs!$F$10=1,Scenarios!$E$6,Scenarios!$E$7) | E17: =E9*(1+D17) | F17: =R9 | G17: =Inputs!$G$10*Scenarios!$E$8 | H17: =F17*G17 | I17: =0 | J17: =0 | K17: =Inputs!$J$10*Scenarios!$E$14*Scenarios!$E$10 | L17: =Inputs!$K$10 | M17: =F17-H17-I17+J17+K17+L17 | N17: =Inputs!$C$10 | O17: =MAX(0,(E17-M17*N17)/N17) | P17: =Inputs!$H$10*IF(Inputs!$I$10=1,Scenarios!$E$9,1) | Q17: =MIN(O17,P17) | R17: =M17+Q17 | S17: =R17*N17 | T17: =E17-S17 | U17: =MAX(0,T17) | V17: =U17*Inputs!$M$10 | W17: =U17-V17 | X17: =(1+Scenarios!$E$11)^B17 | Y17: =((F17*N17+S17)/2)*Inputs!$L$10*X17*Scenarios!$E$15 | Z17: =V17*Inputs!$L$10*X17*Scenarios!$E$12 | AA17: =Q17*Inputs!$N$10 | AB17: =Y17+Z17+AA17 | AC17: =F17+Q17+K17+J17+L17-H17-I17-R17
A18: FY2029 | B18: 3 | C18: Registered Nurse | D18: =Inputs!$E$3+IF(Inputs!$F$3=1,Scenarios!$E$6,Scenarios!$E$7) | E18: =E10*(1+D18) | F18: =R10 | G18: =Inputs!$G$3*Scenarios!$E$8 | H18: =F18*G18 | I18: =0 | J18: =I20 | K18: =Inputs!$J$3*Scenarios!$E$14*Scenarios!$E$10 | L18: =Inputs!$K$3 | M18: =F18-H18-I18+J18+K18+L18 | N18: =Inputs!$C$3 | O18: =MAX(0,(E18-M18*N18)/N18) | P18: =Inputs!$H$3*IF(Inputs!$I$3=1,Scenarios!$E$9,1) | Q18: =MIN(O18,P18) | R18: =M18+Q18 | S18: =R18*N18 | T18: =E18-S18 | U18: =MAX(0,T18) | V18: =U18*Inputs!$M$3 | W18: =U18-V18 | X18: =(1+Scenarios!$E$11)^B18 | Y18: =((F18*N18+S18)/2)*Inputs!$L$3*X18*Scenarios!$E$15 | Z18: =V18*Inputs!$L$3*X18*Scenarios!$E$12 | AA18: =Q18*Inputs!$N$3 | AB18: =Y18+Z18+AA18 | AC18: =F18+Q18+K18+J18+L18-H18-I18-R18
A19: FY2029 | B19: 3 | C19: Midwife | D19: =Inputs!$E$4+IF(Inputs!$F$4=1,Scenarios!$E$6,Scenarios!$E$7) | E19: =E11*(1+D19) | F19: =R11 | G19: =Inputs!$G$4*Scenarios!$E$8 | H19: =F19*G19 | I19: =0 | J19: =0 | K19: =Inputs!$J$4*Scenarios!$E$14*Scenarios!$E$10 | L19: =Inputs!$K$4 | M19: =F19-H19-I19+J19+K19+L19 | N19: =Inputs!$C$4 | O19: =MAX(0,(E19-M19*N19)/N19) | P19: =Inputs!$H$4*IF(Inputs!$I$4=1,Scenarios!$E$9,1) | Q19: =MIN(O19,P19) | R19: =M19+Q19 | S19: =R19*N19 | T19: =E19-S19 | U19: =MAX(0,T19) | V19: =U19*Inputs!$M$4 | W19: =U19-V19 | X19: =(1+Scenarios!$E$11)^B19 | Y19: =((F19*N19+S19)/2)*Inputs!$L$4*X19*Scenarios!$E$15 | Z19: =V19*Inputs!$L$4*X19*Scenarios!$E$12 | AA19: =Q19*Inputs!$N$4 | AB19: =Y19+Z19+AA19 | AC19: =F19+Q19+K19+J19+L19-H19-I19-R19
A20: FY2029 | B20: 3 | C20: Enrolled Nurse | D20: =Inputs!$E$5+IF(Inputs!$F$5=1,Scenarios!$E$6,Scenarios!$E$7) | E20: =E12*(1+D20) | F20: =R12 | G20: =Inputs!$G$5*Scenarios!$E$8 | H20: =F20*G20 | I20: =F20*Scenarios!$E$13 | J20: =0 | K20: =Inputs!$J$5*Scenarios!$E$14*Scenarios!$E$10 | L20: =Inputs!$K$5 | M20: =F20-H20-I20+J20+K20+L20 | N20: =Inputs!$C$5 | O20: =MAX(0,(E20-M20*N20)/N20) | P20: =Inputs!$H$5*IF(Inputs!$I$5=1,Scenarios!$E$9,1) | Q20: =MIN(O20,P20) | R20: =M20+Q20 | S20: =R20*N20 | T20: =E20-S20 | U20: =MAX(0,T20) | V20: =U20*Inputs!$M$5 | W20: =U20-V20 | X20: =(1+Scenarios!$E$11)^B20 | Y20: =((F20*N20+S20)/2)*Inputs!$L$5*X20*Scenarios!$E$15 | Z20: =V20*Inputs!$L$5*X20*Scenarios!$E$12 | AA20: =Q20*Inputs!$N$5 | AB20: =Y20+Z20+AA20 | AC20: =F20+Q20+K20+J20+L20-H20-I20-R20
A21: FY2029 | B21: 3 | C21: Medical Practitioner | D21: =Inputs!$E$6+IF(Inputs!$F$6=1,Scenarios!$E$6,Scenarios!$E$7) | E21: =E13*(1+D21) | F21: =R13 | G21: =Inputs!$G$6*Scenarios!$E$8 | H21: =F21*G21 | I21: =0 | J21: =0 | K21: =Inputs!$J$6*Scenarios!$E$14*Scenarios!$E$10 | L21: =Inputs!$K$6 | M21: =F21-H21-I21+J21+K21+L21 | N21: =Inputs!$C$6 | O21: =MAX(0,(E21-M21*N21)/N21) | P21: =Inputs!$H$6*IF(Inputs!$I$6=1,Scenarios!$E$9,1) | Q21: =MIN(O21,P21) | R21: =M21+Q21 | S21: =R21*N21 | T21: =E21-S21 | U21: =MAX(0,T21) | V21: =U21*Inputs!$M$6 | W21: =U21-V21 | X21: =(1+Scenarios!$E$11)^B21 | Y21: =((F21*N21+S21)/2)*Inputs!$L$6*X21*Scenarios!$E$15 | Z21: =V21*Inputs!$L$6*X21*Scenarios!$E$12 | AA21: =Q21*Inputs!$N$6 | AB21: =Y21+Z21+AA21 | AC21: =F21+Q21+K21+J21+L21-H21-I21-R21
A22: FY2029 | B22: 3 | C22: Allied Health | D22: =Inputs!$E$7+IF(Inputs!$F$7=1,Scenarios!$E$6,Scenarios!$E$7) | E22: =E14*(1+D22) | F22: =R14 | G22: =Inputs!$G$7*Scenarios!$E$8 | H22: =F22*G22 | I22: =0 | J22: =0 | K22: =Inputs!$J$7*Scenarios!$E$14*Scenarios!$E$10 | L22: =Inputs!$K$7 | M22: =F22-H22-I22+J22+K22+L22 | N22: =Inputs!$C$7 | O22: =MAX(0,(E22-M22*N22)/N22) | P22: =Inputs!$H$7*IF(Inputs!$I$7=1,Scenarios!$E$9,1) | Q22: =MIN(O22,P22) | R22: =M22+Q22 | S22: =R22*N22 | T22: =E22-S22 | U22: =MAX(0,T22) | V22: =U22*Inputs!$M$7 | W22: =U22-V22 | X22: =(1+Scenarios!$E$11)^B22 | Y22: =((F22*N22+S22)/2)*Inputs!$L$7*X22*Scenarios!$E$15 | Z22: =V22*Inputs!$L$7*X22*Scenarios!$E$12 | AA22: =Q22*Inputs!$N$7 | AB22: =Y22+Z22+AA22 | AC22: =F22+Q22+K22+J22+L22-H22-I22-R22
A23: FY2029 | B23: 3 | C23: Care Worker | D23: =Inputs!$E$8+IF(Inputs!$F$8=1,Scenarios!$E$6,Scenarios!$E$7) | E23: =E15*(1+D23) | F23: =R15 | G23: =Inputs!$G$8*Scenarios!$E$8 | H23: =F23*G23 | I23: =0 | J23: =0 | K23: =Inputs!$J$8*Scenarios!$E$14*Scenarios!$E$10 | L23: =Inputs!$K$8 | M23: =F23-H23-I23+J23+K23+L23 | N23: =Inputs!$C$8 | O23: =MAX(0,(E23-M23*N23)/N23) | P23: =Inputs!$H$8*IF(Inputs!$I$8=1,Scenarios!$E$9,1) | Q23: =MIN(O23,P23) | R23: =M23+Q23 | S23: =R23*N23 | T23: =E23-S23 | U23: =MAX(0,T23) | V23: =U23*Inputs!$M$8 | W23: =U23-V23 | X23: =(1+Scenarios!$E$11)^B23 | Y23: =((F23*N23+S23)/2)*Inputs!$L$8*X23*Scenarios!$E$15 | Z23: =V23*Inputs!$L$8*X23*Scenarios!$E$12 | AA23: =Q23*Inputs!$N$8 | AB23: =Y23+Z23+AA23 | AC23: =F23+Q23+K23+J23+L23-H23-I23-R23
A24: FY2029 | B24: 3 | C24: Administration | D24: =Inputs!$E$9+IF(Inputs!$F$9=1,Scenarios!$E$6,Scenarios!$E$7) | E24: =E16*(1+D24) | F24: =R16 | G24: =Inputs!$G$9*Scenarios!$E$8 | H24: =F24*G24 | I24: =0 | J24: =0 | K24: =Inputs!$J$9*Scenarios!$E$14*Scenarios!$E$10 | L24: =Inputs!$K$9 | M24: =F24-H24-I24+J24+K24+L24 | N24: =Inputs!$C$9 | O24: =MAX(0,(E24-M24*N24)/N24) | P24: =Inputs!$H$9*IF(Inputs!$I$9=1,Scenarios!$E$9,1) | Q24: =MIN(O24,P24) | R24: =M24+Q24 | S24: =R24*N24 | T24: =E24-S24 | U24: =MAX(0,T24) | V24: =U24*Inputs!$M$9 | W24: =U24-V24 | X24: =(1+Scenarios!$E$11)^B24 | Y24: =((F24*N24+S24)/2)*Inputs!$L$9*X24*Scenarios!$E$15 | Z24: =V24*Inputs!$L$9*X24*Scenarios!$E$12 | AA24: =Q24*Inputs!$N$9 | AB24: =Y24+Z24+AA24 | AC24: =F24+Q24+K24+J24+L24-H24-I24-R24
A25: FY2029 | B25: 3 | C25: Support Services | D25: =Inputs!$E$10+IF(Inputs!$F$10=1,Scenarios!$E$6,Scenarios!$E$7) | E25: =E17*(1+D25) | F25: =R17 | G25: =Inputs!$G$10*Scenarios!$E$8 | H25: =F25*G25 | I25: =0 | J25: =0 | K25: =Inputs!$J$10*Scenarios!$E$14*Scenarios!$E$10 | L25: =Inputs!$K$10 | M25: =F25-H25-I25+J25+K25+L25 | N25: =Inputs!$C$10 | O25: =MAX(0,(E25-M25*N25)/N25) | P25: =Inputs!$H$10*IF(Inputs!$I$10=1,Scenarios!$E$9,1) | Q25: =MIN(O25,P25) | R25: =M25+Q25 | S25: =R25*N25 | T25: =E25-S25 | U25: =MAX(0,T25) | V25: =U25*Inputs!$M$10 | W25: =U25-V25 | X25: =(1+Scenarios!$E$11)^B25 | Y25: =((F25*N25+S25)/2)*Inputs!$L$10*X25*Scenarios!$E$15 | Z25: =V25*Inputs!$L$10*X25*Scenarios!$E$12 | AA25: =Q25*Inputs!$N$10 | AB25: =Y25+Z25+AA25 | AC25: =F25+Q25+K25+J25+L25-H25-I25-R25

Sheet Summary
A1: Summary - selected scenario: | C1: =Scenarios!C3
A3: Metric | B3: FY2027 | C3: FY2028 | D3: FY2029
A4: Demand FTE | B4: =SUMIFS(Model!$E:$E,Model!$A:$A,"FY2027") | C4: =SUMIFS(Model!$E:$E,Model!$A:$A,"FY2028") | D4: =SUMIFS(Model!$E:$E,Model!$A:$A,"FY2029")
A5: Supply FTE | B5: =SUMIFS(Model!$S:$S,Model!$A:$A,"FY2027") | C5: =SUMIFS(Model!$S:$S,Model!$A:$A,"FY2028") | D5: =SUMIFS(Model!$S:$S,Model!$A:$A,"FY2029")
A6: Gap FTE | B6: =SUMIFS(Model!$T:$T,Model!$A:$A,"FY2027") | C6: =SUMIFS(Model!$T:$T,Model!$A:$A,"FY2028") | D6: =SUMIFS(Model!$T:$T,Model!$A:$A,"FY2029")
A7: Shortage FTE | B7: =SUMIFS(Model!$U:$U,Model!$A:$A,"FY2027") | C7: =SUMIFS(Model!$U:$U,Model!$A:$A,"FY2028") | D7: =SUMIFS(Model!$U:$U,Model!$A:$A,"FY2029")
A8: Required hires | B8: =SUMIFS(Model!$O:$O,Model!$A:$A,"FY2027") | C8: =SUMIFS(Model!$O:$O,Model!$A:$A,"FY2028") | D8: =SUMIFS(Model!$O:$O,Model!$A:$A,"FY2029")
A9: Capacity | B9: =SUMIFS(Model!$P:$P,Model!$A:$A,"FY2027") | C9: =SUMIFS(Model!$P:$P,Model!$A:$A,"FY2028") | D9: =SUMIFS(Model!$P:$P,Model!$A:$A,"FY2029")
A10: Hires | B10: =SUMIFS(Model!$Q:$Q,Model!$A:$A,"FY2027") | C10: =SUMIFS(Model!$Q:$Q,Model!$A:$A,"FY2028") | D10: =SUMIFS(Model!$Q:$Q,Model!$A:$A,"FY2029")
A11: Separations | B11: =SUMIFS(Model!$H:$H,Model!$A:$A,"FY2027") | C11: =SUMIFS(Model!$H:$H,Model!$A:$A,"FY2028") | D11: =SUMIFS(Model!$H:$H,Model!$A:$A,"FY2029")
A12: HC end | B12: =SUMIFS(Model!$R:$R,Model!$A:$A,"FY2027") | C12: =SUMIFS(Model!$R:$R,Model!$A:$A,"FY2028") | D12: =SUMIFS(Model!$R:$R,Model!$A:$A,"FY2029")
A13: Agency FTE | B13: =SUMIFS(Model!$V:$V,Model!$A:$A,"FY2027") | C13: =SUMIFS(Model!$V:$V,Model!$A:$A,"FY2028") | D13: =SUMIFS(Model!$V:$V,Model!$A:$A,"FY2029")
A14: Unfilled FTE | B14: =SUMIFS(Model!$W:$W,Model!$A:$A,"FY2027") | C14: =SUMIFS(Model!$W:$W,Model!$A:$A,"FY2028") | D14: =SUMIFS(Model!$W:$W,Model!$A:$A,"FY2029")
A15: Employee cost | B15: =SUMIFS(Model!$Y:$Y,Model!$A:$A,"FY2027") | C15: =SUMIFS(Model!$Y:$Y,Model!$A:$A,"FY2028") | D15: =SUMIFS(Model!$Y:$Y,Model!$A:$A,"FY2029")
A16: Agency cost | B16: =SUMIFS(Model!$Z:$Z,Model!$A:$A,"FY2027") | C16: =SUMIFS(Model!$Z:$Z,Model!$A:$A,"FY2028") | D16: =SUMIFS(Model!$Z:$Z,Model!$A:$A,"FY2029")
A17: Recruitment cost | B17: =SUMIFS(Model!$AA:$AA,Model!$A:$A,"FY2027") | C17: =SUMIFS(Model!$AA:$AA,Model!$A:$A,"FY2028") | D17: =SUMIFS(Model!$AA:$AA,Model!$A:$A,"FY2029")
A18: Total cost | B18: =SUMIFS(Model!$AB:$AB,Model!$A:$A,"FY2027") | C18: =SUMIFS(Model!$AB:$AB,Model!$A:$A,"FY2028") | D18: =SUMIFS(Model!$AB:$AB,Model!$A:$A,"FY2029")
A19: Gap % of demand | B19: =B6/B4 | C19: =C6/C4 | D19: =D6/D4
A20: Capacity utilisation (required / capacity) | B20: =B8/B9 | C20: =C8/C9 | D20: =D8/D9
A22: 3-year total cost | B22: =SUM(B18:D18)
A23: Max |stock-flow identity error| (should be 0) | B23: =MAX(Model!AC2:AC25)-MIN(Model!AC2:AC25)

Sheet Sensitivity
A1: Sensitivity (computed by src/scenario_model.py at job family x location level; values, not formulas)
A3: Assumption | B3: FY2029 shortage FTE (low) | C3: FY2029 shortage FTE (high) | D3: Swing (FTE) | E3: 3-yr cost low ($) | F3: 3-yr cost high ($)
A4: Recruitment capacity x0.8 / x1.2 | B4: 95.25 | C4: 12.98 | D4: 82.27 | E4: 8.0477227e+08 | F4: 8.129301e+08
A5: Attrition rate x0.8 / x1.2 | B5: 13.63 | C5: 75.2 | D5: 61.57 | E5: 8.1137965e+08 | F5: 8.0836196e+08
A6: FTE per head x0.95 / x1.05 | B6: 55.62 | C6: 16.05 | D6: 39.57 | E6: 8.0075631e+08 | F6: 8.1925706e+08
A7: Demand growth -1pp / +1pp | B7: 18.67 | C7: 42.44 | D7: 23.77 | E7: 7.9871093e+08 | F7: 8.2220129e+08
A8: EN->RN conversion x0 / x2 | B8: 23.11 | C8: 33.29 | D8: 10.18 | E8: 8.1072551e+08 | F8: 8.103016e+08
A9: Wage growth -1pp / +1pp | B9: 27.91 | C9: 27.91 | D9: 0 | E9: 7.9472546e+08 | F9: 8.2624436e+08
A10: Agency premium 1.3 / 2.0 | B10: 27.91 | C10: 27.91 | D10: 0 | E10: 8.0757779e+08 | F10: 8.1318417e+08
A13: Monte Carlo (2,000 draws, Baseline structure)
A14: Outcome | B14: P10 | C14: P50 | D14: P90
A15: shortage_FY2029 | B15: 17.7 | C15: 47.1 | D15: 110.6
A16: gap_FY2029 | B16: 17.7 | C16: 47.1 | D16: 110.6
A17: agency_cost_3y | B17: 10244470 | C17: 17481503 | D17: 30267888
A18: total_cost_3y | B18: 7.9665652e+08 | C18: 8.0785298e+08 | D18: 8.1899094e+08

Sheet Evidence
A1: Real public data behind the assumptions (see docs/source_register.md for links)
A3: assumption | B3: evidence | C3: provenance | D3: value
A4: Demand growth (baseline) | B4: JSA Employment Projections 2025-35 10-yr CAGR by occupation x WA/AUS adjustment | C4: REAL | D4: Registered Nurse: 2.37%; Midwife: 2.43%; Enrolled Nurse: 1.98%; Medical Practitioner: 2.92%; Allied Health: 3.03%; Care Worker: 1.84%; Administration: 0.94%; Support Services: 0.50%
A5: WA adjustment factor | B5: JSA projections Table 4 (WA vs AUS 10-yr growth) | C5: REAL | D5: 1.0003
A6: Demand uplift (Growth scenario) | B6: Service expansion; bounded by ABS HCSA filled-jobs 5-yr CAGR 5.6% | C6: ILLUSTRATIVE | D6: +2.0pp clinical, +0.5pp non-clinical
A7: Attrition rate | B7: KHS FY2025-26 cell rates, credibility-weighted (K=60) to family rate | C7: SYNTHETIC (measured) | D7: org avg 14.5%
A8: Attrition multiplier (Constraint) | B8: KHS FY2023 (tight market) / FY2026 turnover | C8: SYNTHETIC (measured) | D8: 1.224
A9: Recruitment capacity | B9: Best annual external hires FY2023-26 per cell (demonstrated throughput) | C9: SYNTHETIC (measured) | D9: 478 hires/yr
A10: Capacity multiplier (Constraint, shortage occupations) | B10: JSA OSL 2026 fill rate shortage/no-shortage 57%/78% | C10: REAL | D10: 0.731
A11: Graduate RN intake | B11: KHS average FY2023-26 | C11: SYNTHETIC (measured) | D11: 16/yr; Constraint x0.75 (illustrative)
A12: EN->RN conversion | B12: KHS role changes / EN headcount | C12: SYNTHETIC (measured) | D12: 5.51%/yr
A13: Wage growth | B13: ABS WPI HCSA YoY, average of last 8 quarters | C13: REAL | D13: 3.71%/yr; Constraint +1pp (illustrative)
A14: On-cost factor | B14: 12% super guarantee (legislated) + payroll tax/workers comp/leave (assumed) | C14: ILLUSTRATIVE | D14: 1.25
... A19: Intervention effects and costs | B19: Assumed programme effects for option testing | C19: ILLUSTRATIVE | D19: M1 Retention programme (clinical attrition -15%): $1,950,000/yr; M2 Regional recruitment uplift (+30% capacity): $260,000/yr; M3 Grow-your-own (EN->RN 2x, +12 graduates): $480,000/yr; M4 Agency panel (premium 1.65 -> 1.45): $60,000/yr

Sheet Checks
A1: Python engine reference values (family level) - Summary sheet should match for the selected scenario
A3: scenario | B3: year | C3: Demand FTE | D3: Supply FTE | E3: Gap FTE | F3: Hires | G3: Agency cost | H3: Total cost
A4: A Baseline | B4: FY2027 | C4: 1735.4763 | D4: 1713.1034 | E4: 22.372858 | F4: 378.86778 | G4: 3788336.1 | H4: 2.5388483e+08
A5: A Baseline | B5: FY2028 | C5: 1769.9189 | D5: 1760.9696 | E5: 8.9493343 | F5: 349.93064 | G5: 2698347.8 | H5: 2.7145127e+08
A6: A Baseline | B6: FY2029 | C6: 1805.1465 | D6: 1797.0517 | E6: 8.0948401 | F6: 344.10074 | G6: 2531256.2 | H6: 2.8837947e+08
A7: B Growth | B7: FY2027 | C7: 1763.5813 | D7: 1729.6084 | E7: 33.972858 | F7: 399.01079 | G7: 5113035.5 | H7: 2.5660522e+08
A8: B Growth | B8: FY2028 | C8: 1827.9189 | D8: 1802.8129 | E8: 25.105942 | F8: 383.9279 | G8: 5057920.9 | H8: 2.7843332e+08
A9: B Growth | B9: FY2029 | C9: 1894.9239 | D9: 1870.4415 | E9: 24.482415 | F9: 390.95147 | G9: 5776685.6 | H9: 3.0066351e+08
A10: C Constraint | B10: FY2027 | C10: 1735.4763 | D10: 1647.839 | E10: 87.637293 | F10: 362.64627 | G10: 9665787.7 | H10: 2.572405e+08
A11: C Constraint | B11: FY2028 | C11: 1769.9189 | D11: 1655.5888 | E11: 114.33007 | F11: 348.20555 | G11: 13749665 | H11: 2.742454e+08
A12: C Constraint | B12: FY2029 | C12: 1805.1465 | D12: 1661.8661 | E12: 143.28039 | F12: 345.9434 | G12: 18191776 | H12: 2.9175622e+08
